{
  "openapi": "3.0.1",
  "info": {
    "title": "MediathekArrApi | v1",
    "version": "1.0.0"
  },
  "paths": {
    "/api/Series": {
      "get": {
        "tags": [
          "Series"
        ],
        "parameters": [
          {
            "name": "tvdbId",
            "in": "query",
            "schema": {
              "type": "integer",
              "format": "int32"
            }
          }
        ],
        "responses": {
          "200": {
            "description": "OK",
            "content": {
              "text/plain": {
                "schema": {
                  "$ref": "#/components/schemas/Series"
                }
              },
              "application/json": {
                "schema": {
                  "$ref": "#/components/schemas/Series"
                }
              },
              "text/json": {
                "schema": {
                  "$ref": "#/components/schemas/Series"
                }
              }
            }
          }
        }
      }
    }
  },
  "components": {
    "schemas": {
      "Episode": {
        "type": "object",
        "properties": {
          "id": {
            "type": "integer",
            "format": "int32"
          },
          "seriesId": {
            "type": "integer",
            "format": "int32"
          },
          "name": {
            "type": "string",
            "nullable": true
          },
          "aired": {
            "type": "string",
            "format": "date-time",
            "nullable": true
          },
          "runtime": {
            "type": "integer",
            "format": "int32",
            "nullable": true
          },
          "seasonNumber": {
            "type": "integer",
            "format": "int32",
            "nullable": true
          },
          "episodeNumber": {
            "type": "integer",
            "format": "int32",
            "nullable": true
          }
        }
      },
      "Series": {
        "type": "object",
        "properties": {
          "seriesId": {
            "type": "integer",
            "format": "int32"
          },
          "name": {
            "type": "string",
            "nullable": true
          },
          "germanName": {
            "type": "string",
            "nullable": true
          },
          "aliases": {
            "type": "string",
            "nullable": true
          },
          "lastUpdated": {
            "type": "string",
            "format": "date-time"
          },
          "nextAired": {
            "type": "string",
            "format": "date-time",
            "nullable": true
          },
          "lastAired": {
            "type": "string",
            "format": "date-time",
            "nullable": true
          },
          "cacheExpiry": {
            "type": "string",
            "format": "date-time"
          },
          "episodes": {
            "type": "array",
            "items": {
              "$ref": "#/components/schemas/Episode"
            }
          }
        }
      }
    }
  },
  "tags": [
    {
      "name": "Series"
    }
  ]
}